python_750_plc-0.2.6.dist-info/licenses/LICENSE
wg750xxx/README.md
wg750xxx/__init__.py
wg750xxx/const.py
wg750xxx/exceptions.py
wg750xxx/misc.py
wg750xxx/settings.py
wg750xxx/wg750xxx.py
wg750xxx/modbus/__init__.py
wg750xxx/modbus/exceptions.py
wg750xxx/modbus/registers.py
wg750xxx/modbus/state.py
wg750xxx/modules/__init__.py
wg750xxx/modules/channel.py
wg750xxx/modules/exceptions.py
wg750xxx/modules/identifier.py
wg750xxx/modules/module.py
wg750xxx/modules/spec.py
wg750xxx/modules/analog/__init__.py
wg750xxx/modules/analog/channels.py
wg750xxx/modules/analog/modules.py
wg750xxx/modules/controller/__init__.py
wg750xxx/modules/controller/modules.py
wg750xxx/modules/counter/__init__.py
wg750xxx/modules/counter/channels.py
wg750xxx/modules/counter/counter_communication.py
wg750xxx/modules/counter/modules.py
wg750xxx/modules/dali/__init__.py
wg750xxx/modules/dali/channel_base.py
wg750xxx/modules/dali/channel_commands.py
wg750xxx/modules/dali/channel_setup.py
wg750xxx/modules/dali/channel_status.py
wg750xxx/modules/dali/channels.py
wg750xxx/modules/dali/control_byte.py
wg750xxx/modules/dali/dali_communication.py
wg750xxx/modules/dali/exceptions.py
wg750xxx/modules/dali/misc.py
wg750xxx/modules/dali/module_base.py
wg750xxx/modules/dali/module_commands.py
wg750xxx/modules/dali/module_setup.py
wg750xxx/modules/dali/module_status.py
wg750xxx/modules/dali/modules.py
wg750xxx/modules/dali/status_byte.py
wg750xxx/modules/dali/tools.py
wg750xxx/modules/digital/__init__.py
wg750xxx/modules/digital/channels.py
wg750xxx/modules/digital/modules.py
python_750_plc-0.2.6.dist-info/METADATA
python_750_plc-0.2.6.dist-info/WHEEL
python_750_plc-0.2.6.dist-info/top_level.txt
python_750_plc-0.2.6.dist-info/RECORD
