Metadata-Version: 2.4
Name: python-750-plc
Version: 0.2.6
Summary: Python module for interacting with WAGO 750 series PLCs through Modbus TCP
Home-page: https://github.com/bastibrunner/python-750-plc
Author: Bastian Brunner
Author-email: Bastian Brunner <bb@intern-net.de>
License-Expression: MIT
Keywords: home,automation,plc,wago
Classifier: Development Status :: 4 - Beta
Classifier: Intended Audience :: Developers
Classifier: Operating System :: OS Independent
Classifier: Programming Language :: Python :: 3
Classifier: Topic :: Home Automation
Classifier: Topic :: System :: Hardware
Requires-Python: >=3.6
License-File: LICENSE
Requires-Dist: numpy>=2.2.2
Requires-Dist: pydantic>=2.10.6
Requires-Dist: pymodbus>=3.8.3
Dynamic: author
Dynamic: home-page
Dynamic: license-file
Dynamic: requires-python
